eminus/README.md
eminus/__init__.py
eminus/__init__.pyi
eminus/atoms.py
eminus/atoms.pyi
eminus/backend.py
eminus/backend.pyi
eminus/band_minimizer.py
eminus/band_minimizer.pyi
eminus/cell.py
eminus/cell.pyi
eminus/config.py
eminus/config.pyi
eminus/data.py
eminus/data.pyi
eminus/dft.py
eminus/dft.pyi
eminus/domains.py
eminus/domains.pyi
eminus/energies.py
eminus/energies.pyi
eminus/gga.py
eminus/gga.pyi
eminus/gth.py
eminus/gth.pyi
eminus/kpoints.py
eminus/kpoints.pyi
eminus/localizer.py
eminus/localizer.pyi
eminus/logger.py
eminus/logger.pyi
eminus/minimizer.py
eminus/minimizer.pyi
eminus/occupations.py
eminus/occupations.pyi
eminus/operators.py
eminus/operators.pyi
eminus/orbitals.py
eminus/orbitals.pyi
eminus/potentials.py
eminus/potentials.pyi
eminus/py.typed
eminus/scf.py
eminus/scf.pyi
eminus/testing.py
eminus/testing.pyi
eminus/tools.py
eminus/tools.pyi
eminus/units.py
eminus/units.pyi
eminus/utils.py
eminus/utils.pyi
eminus/version.py
eminus/version.pyi
eminus/extras/README.md
eminus/extras/__init__.py
eminus/extras/__init__.pyi
eminus/extras/d3.py
eminus/extras/d3.pyi
eminus/extras/fods.py
eminus/extras/fods.pyi
eminus/extras/gui.py
eminus/extras/gui.pyi
eminus/extras/hdf5.py
eminus/extras/hdf5.pyi
eminus/extras/libxc.py
eminus/extras/libxc.pyi
eminus/io/README.md
eminus/io/__init__.py
eminus/io/__init__.pyi
eminus/io/cube.py
eminus/io/cube.pyi
eminus/io/gth.py
eminus/io/gth.pyi
eminus/io/json.py
eminus/io/json.pyi
eminus/io/pdb.py
eminus/io/pdb.pyi
eminus/io/poscar.py
eminus/io/poscar.pyi
eminus/io/traj.py
eminus/io/traj.pyi
eminus/io/xyz.py
eminus/io/xyz.pyi
eminus/psp/README.md
eminus/psp/__init__.py
eminus/psp/__init__.pyi
eminus/psp/pade/Ac-q11
eminus/psp/pade/Ac-q29
eminus/psp/pade/Ag-q1
eminus/psp/pade/Ag-q11
eminus/psp/pade/Ag-q19
eminus/psp/pade/Al-q3
eminus/psp/pade/Am-q17
eminus/psp/pade/Am-q35
eminus/psp/pade/Ar-q8
eminus/psp/pade/As-q5
eminus/psp/pade/At-q7
eminus/psp/pade/Au-q1
eminus/psp/pade/Au-q11
eminus/psp/pade/Au-q19
eminus-3.2.0.dist-info/METADATA
eminus-3.2.0.dist-info/WHEEL
eminus-3.2.0.dist-info/licenses/LICENSE
eminus-3.2.0.dist-info/RECORD
