Metadata-Version: 2.4
Name: eminus
Version: 3.2.0
Summary: Pythonic electronic structure theory.
Project-URL: source, https://gitlab.com/wangenau/eminus
Project-URL: changelog, https://wangenau.gitlab.io/eminus/changelog.html
Project-URL: documentation, https://wangenau.gitlab.io/eminus
Project-URL: issues, https://gitlab.com/wangenau/eminus/-/issues
Author-email: Wanja Timm Schulze <wangenau@protonmail.com>
License-Expression: Apache-2.0
License-File: LICENSE
Keywords: density-functional-theory,education,electronic-structure,python
Classifier: Development Status :: 5 - Production/Stable
Classifier: Intended Audience :: Developers
Classifier: Intended Audience :: Education
Classifier: Intended Audience :: Science/Research
Classifier: Operating System :: MacOS
Classifier: Operating System :: Microsoft
Classifier: Operating System :: POSIX
Classifier: Operating System :: Unix
Classifier: Programming Language :: Python
Classifier: Programming Language :: Python :: 3
Classifier: Programming Language :: Python :: 3 :: Only
Classifier: Programming Language :: Python :: 3.9
Classifier: Programming Language :: Python :: 3.10
Classifier: Programming Language :: Python :: 3.11
Classifier: Programming Language :: Python :: 3.12
Classifier: Programming Language :: Python :: 3.13
Classifier: Programming Language :: Python :: 3.14
Classifier: Programming Language :: Python :: Free Threading
Classifier: Topic :: Education
Classifier: Topic :: Scientific/Engineering
Classifier: Topic :: Scientific/Engineering :: Chemistry
Classifier: Topic :: Scientific/Engineering :: Physics
Classifier: Topic :: Software Development
Classifier: Typing :: Typed
Requires-Python: >=3.9
Requires-Dist: numpy>=2
Requires-Dist: scipy>=1.13
Provides-Extra: all
Requires-Dist: array-api-compat>=1.6; extra == 'all'
Requires-Dist: dftd3>=1.1; extra == 'all'
Requires-Dist: h5py>=3.11; extra == 'all'
Requires-Dist: nglview>=2.6.5; extra == 'all'
Requires-Dist: plotly>=4.5; extra == 'all'
Requires-Dist: pyscf>=2.6.2; extra == 'all'
Requires-Dist: torch>=2.5; extra == 'all'
Provides-Extra: d3
Requires-Dist: dftd3>=1.1; extra == 'd3'
Provides-Extra: fods
Requires-Dist: pyscf>=2.6.2; extra == 'fods'
Provides-Extra: gui
Requires-Dist: nglview>=2.6.5; extra == 'gui'
Requires-Dist: plotly>=4.5; extra == 'gui'
Provides-Extra: hdf5
Requires-Dist: h5py>=3.11; extra == 'hdf5'
Provides-Extra: libxc
Requires-Dist: pyscf>=2.6.2; extra == 'libxc'
Provides-Extra: torch
Requires-Dist: array-api-compat>=1.6; extra == 'torch'
Requires-Dist: torch>=2.5; extra == 'torch'
